homewizard_energy/__init__.py
homewizard_energy/const.py
homewizard_energy/errors.py
homewizard_energy/homewizard_energy.py
homewizard_energy/models.py
homewizard_energy/py.typed
homewizard_energy/utils.py
homewizard_energy/v1/__init__.py
homewizard_energy/v1/const.py
homewizard_energy/v2/__init__.py
homewizard_energy/v2/cacert.py
homewizard_energy/v2/const.py
python_homewizard_energy-10.0.0.dist-info/METADATA
python_homewizard_energy-10.0.0.dist-info/WHEEL
python_homewizard_energy-10.0.0.dist-info/licenses/LICENSE
python_homewizard_energy-10.0.0.dist-info/RECORD
