Metadata-Version: 2.4
Name: python-homewizard-energy
Version: 10.0.0
Summary: Asynchronous Python client for the HomeWizard Energy
License: Apache-2.0
License-File: LICENSE
Author: DCSBL
Maintainer: DCSBL
Requires-Python: >=3.12,<4.0
Classifier: License :: OSI Approved :: Apache Software License
Classifier: Programming Language :: Python :: 3
Classifier: Programming Language :: Python :: 3.12
Classifier: Programming Language :: Python :: 3.13
Classifier: Programming Language :: Python :: 3.14
Requires-Dist: aiohttp (>=3.0.0)
Requires-Dist: async-timeout (>=4.0.3,<6.0.0)
Requires-Dist: awesomeversion (>=24.6.0)
Requires-Dist: backoff (>=2.2.1,<3.0.0)
Requires-Dist: mashumaro (>=3.15,<4.0)
Requires-Dist: multidict (>=6.0.5,<7.0.0)
Requires-Dist: orjson (>=3.10,<4.0)
Project-URL: Bug Tracker, https://github.com/homewizard/python-homewizard-energy/issues
Project-URL: Changelog, https://github.com/homewizard/python-homewizard-energy/releases
Project-URL: Documentation, https://github.com/homewizard/python-homewizard-energy
Project-URL: Homepage, https://github.com/homewizard/python-homewizard-energy
Project-URL: Repository, https://github.com/homewizard/python-homewizard-energy
